CS220-Computer_Organization/Assignment2/8_bit_Johnson_Counter/A2Q2_Eight_Bit_Johnson_Counter.v
module D_FF(
    input clk,
    input reset,
    input d,
    output q
);
    reg q;
    always @(posedge clk or posedge reset) begin
        if(reset) 
            q <= 1'b0;
        else 
            q <= d;
    end
endmodule

module eight_bit_johnson_counter(
    input clk,
    input reset,
    output [7:0] q
);

    generate
        genvar i;
        for(i=0;i<8;i=i+1) begin
            if(i==0) begin
                D_FF dff1(clk,reset,~(q[7]),q[0]);
            end
            else begin
                D_FF dff2(clk,reset,q[i-1],q[i]);
            end
        end
    endgenerate

endmodule

CS220-Computer_Organization/Assignment2/8_bit_Johnson_Counter/A2Q2_Eight_Bit_Johnson_Counter_Top.v
`include "A2Q2_Eight_Bit_Johnson_Counter.v"

module stimulus;

    reg clk;
    reg reset;

    wire [7:0] q;

    eight_bit_johnson_counter counter1(clk,reset,q);

    initial begin
        clk=1'b0;
    end

    always  begin
        #5 clk=~clk;
    end

    initial begin
        
        reset=1'b1;
        #15 reset=1'b0;
        #180 reset=1'b1;
        #10 reset=1'b0;
        #10 $finish;
    end


    initial begin
        $dumpfile("8_bit_johnson_counter.vcd");
        $dumpvars(0,stimulus);
    end

    initial begin
        $display("\t \t \t \t \t q7 q6 q5 q4 q3 q2 q1 q0  ");
        $monitor($time," reset = %b,Output q = %b  %b  %b  %b  %b  %b  %b  %b",reset,q[7],q[6],q[5],q[4],q[3],q[2],q[1],q[0]); 
    end

endmodule

CS220-Computer_Organization/Assignment2/8_bit_Johnson_Counter/8_bit_johnson_counter.vcd
$date
	Mon Feb 14 16:23:38 2022
$end
$version
	Icarus Verilog
$end
$timescale
	1s
$end
$scope module stimulus $end
$var wire 8 ! q [7:0] $end
$var reg 1 " clk $end
$var reg 1 # reset $end
$scope module counter1 $end
$var wire 1 " clk $end
$var wire 1 # reset $end
$var wire 8 $ q [7:0] $end
$scope begin genblk1[0] $end
$scope begin genblk1 $end
$scope module dff1 $end
$var wire 1 " clk $end
$var wire 1 % d $end
$var wire 1 # reset $end
$var reg 1 & q $end
$upscope $end
$upscope $end
$upscope $end
$scope begin genblk1[1] $end
$scope begin genblk1 $end
$scope module dff2 $end
$var wire 1 " clk $end
$var wire 1 ' d $end
$var wire 1 # reset $end
$var reg 1 ( q $end
$upscope $end
$upscope $end
$upscope $end
$scope begin genblk1[2] $end
$scope begin genblk1 $end
$scope module dff2 $end
$var wire 1 " clk $end
$var wire 1 ) d $end
$var wire 1 # reset $end
$var reg 1 * q $end
$upscope $end
$upscope $end
$upscope $end
$scope begin genblk1[3] $end
$scope begin genblk1 $end
$scope module dff2 $end
$var wire 1 " clk $end
$var wire 1 + d $end
$var wire 1 # reset $end
$var reg 1 , q $end
$upscope $end
$upscope $end
$upscope $end
$scope begin genblk1[4] $end
$scope begin genblk1 $end
$scope module dff2 $end
$var wire 1 " clk $end
$var wire 1 - d $end
$var wire 1 # reset $end
$var reg 1 . q $end
$upscope $end
$upscope $end
$upscope $end
$scope begin genblk1[5] $end
$scope begin genblk1 $end
$scope module dff2 $end
$var wire 1 " clk $end
$var wire 1 / d $end
$var wire 1 # reset $end
$var reg 1 0 q $end
$upscope $end
$upscope $end
$upscope $end
$scope begin genblk1[6] $end
$scope begin genblk1 $end
$scope module dff2 $end
$var wire 1 " clk $end
$var wire 1 1 d $end
$var wire 1 # reset $end
$var reg 1 2 q $end
$upscope $end
$upscope $end
$upscope $end
$scope begin genblk1[7] $end
$scope begin genblk1 $end
$scope module dff2 $end
$var wire 1 " clk $end
$var wire 1 3 d $end
$var wire 1 # reset $end
$var reg 1 4 q $end
$upscope $end
$upscope $end
$upscope $end
$upscope $end
$upscope $end
$enddefinitions $end
#0
$dumpvars
04
03
02
01
00
0/
0.
0-
0,
0+
0*
0)
0(
0'
0&
1%
b0 $
1#
0"
b0 !
$end
#5
1"
#10
0"
#15
1'
b1 !
b1 $
1&
1"
0#
#20
0"
#25
1)
b11 !
b11 $
1(
1"
#30
0"
#35
1+
b111 !
b111 $
1*
1"
#40
0"
#45
1-
b1111 !
b1111 $
1,
1"
#50
0"
#55
1/
b11111 !
b11111 $
1.
1"
#60
0"
#65
11
b111111 !
b111111 $
10
1"
#70
0"
#75
13
b1111111 !
b1111111 $
12
1"
#80
0"
#85
0%
b11111111 !
b11111111 $
14
1"
#90
0"
#95
0'
b11111110 !
b11111110 $
0&
1"
#100
0"
#105
0)
b11111100 !
b11111100 $
0(
1"
#110
0"
#115
0+
b11111000 !
b11111000 $
0*
1"
#120
0"
#125
0-
b11110000 !
b11110000 $
0,
1"
#130
0"
#135
0/
b11100000 !
b11100000 $
0.
1"
#140
0"
#145
01
b11000000 !
b11000000 $
00
1"
#150
0"
#155
03
b10000000 !
b10000000 $
02
1"
#160
0"
#165
1%
b0 !
b0 $
04
1"
#170
0"
#175
1'
b1 !
b1 $
1&
1"
#180
0"
#185
1)
b11 !
b11 $
1(
1"
#190
0"
#195
0'
0)
0&
b0 !
b0 $
0(
1"
1#
#200
0"
#205
1'
b1 !
b1 $
1&
1"
0#
#210
0"
#215
1)
b11 !
b11 $
1(
1"
