CS220-Computer_Organization/Assignment2/8_bit_johnson_counter_better/johnson.v
module johnson(clk,reset,out);
input clk,reset;
output reg [7:0] out;
integer left = -1, right = -1;

always @ (posedge clk or posedge reset)  begin
        if(reset)
        begin
                left = -1;
                right = -1;
                out<=0;
        end
        else begin
        if(left<7) begin
            left = left + 1;
            out[left]<=1'b1;
        end else begin
            if(right==7) begin
                out <= 0;
                left=-1;
                right=-1;
            end else begin
                right = right + 1;
                out[right]<=1'b0;
            end
        end
  end
end
endmodule   //johnson

CS220-Computer_Organization/Assignment2/8_bit_johnson_counter_better/test.v

`include "johnson.v"

module stimulus;

    reg clk;
    reg reset;

    wire [7:0] q;

    johnson counter1(clk,reset,q);

    initial begin
        clk=1'b0;
    end

    always  begin
        #5 clk=~clk;
    end

    initial begin
        
        reset=1'b1;
        #15 reset=1'b0;
        #180 reset=1'b1;
        #10 reset=1'b0;
        #100 $finish;
    end


    initial begin
        $dumpfile("johnson.vcd");
        $dumpvars(0,stimulus);
    end

    initial begin
        $display("\t \t \t \t \t q7 q6 q5 q4 q3 q2 q1 q0  ");
        $monitor($time," reset = %b,Output q = %b  %b  %b  %b  %b  %b  %b  %b",reset,q[7],q[6],q[5],q[4],q[3],q[2],q[1],q[0]); 
    end

endmodule

CS220-Computer_Organization/Assignment2/8_bit_johnson_counter_better/johnson.vcd
$date
	Sat Feb  5 17:55:30 2022
$end
$version
	Icarus Verilog
$end
$timescale
	1s
$end
$scope module stimulus $end
$var wire 8 ! q [7:0] $end
$var reg 1 " clk $end
$var reg 1 # reset $end
$scope module counter1 $end
$var wire 1 " clk $end
$var wire 1 # reset $end
$var reg 8 $ out [7:0] $end
$var integer 32 % left [31:0] $end
$var integer 32 & right [31:0] $end
$upscope $end
$upscope $end
$enddefinitions $end
#0
$dumpvars
b11111111111111111111111111111111 &
b11111111111111111111111111111111 %
b0 $
1#
0"
b0 !
$end
#5
1"
#10
0"
#15
b1 !
b1 $
b0 %
1"
0#
#20
0"
#25
b11 !
b11 $
b1 %
1"
#30
0"
#35
b111 !
b111 $
b10 %
1"
#40
0"
#45
b1111 !
b1111 $
b11 %
1"
#50
0"
#55
b11111 !
b11111 $
b100 %
1"
#60
0"
#65
b111111 !
b111111 $
b101 %
1"
#70
0"
#75
b1111111 !
b1111111 $
b110 %
1"
#80
0"
#85
b11111111 !
b11111111 $
b111 %
1"
#90
0"
#95
b11111110 !
b11111110 $
b0 &
1"
#100
0"
#105
b11111100 !
b11111100 $
b1 &
1"
#110
0"
#115
b11111000 !
b11111000 $
b10 &
1"
#120
0"
#125
b11110000 !
b11110000 $
b11 &
1"
#130
0"
#135
b11100000 !
b11100000 $
b100 &
1"
#140
0"
#145
b11000000 !
b11000000 $
b101 &
1"
#150
0"
#155
b10000000 !
b10000000 $
b110 &
1"
#160
0"
#165
b0 !
b0 $
b111 &
1"
#170
0"
#175
b11111111111111111111111111111111 &
b11111111111111111111111111111111 %
1"
#180
0"
#185
b1 !
b1 $
b0 %
1"
#190
0"
#195
b0 !
b0 $
b11111111111111111111111111111111 %
1"
1#
#200
0"
#205
b1 !
b1 $
b0 %
1"
0#
#210
0"
#215
b11 !
b11 $
b1 %
1"
#220
0"
#225
b111 !
b111 $
b10 %
1"
#230
0"
#235
b1111 !
b1111 $
b11 %
1"
#240
0"
#245
b11111 !
b11111 $
b100 %
1"
#250
0"
#255
b111111 !
b111111 $
b101 %
1"
#260
0"
#265
b1111111 !
b1111111 $
b110 %
1"
#270
0"
#275
b11111111 !
b11111111 $
b111 %
1"
#280
0"
#285
b11111110 !
b11111110 $
b0 &
1"
#290
0"
#295
b11111100 !
b11111100 $
b1 &
1"
#300
0"
#305
b11111000 !
b11111000 $
b10 &
1"
